mace/__init__.py
mace/__main__.py
mace/_cli_quickstart.py
mace/_complex_init_files.py
mace/_complex_init_mols.py
mace/_complex_object.py
mace/_parameters.py
mace/_smiles_parsing.py
mace/_substituents.py
mace/_supporting_functions.py
epic_mace-0.5.0.dist-info/LICENSE
epic_mace-0.5.0.dist-info/METADATA
epic_mace-0.5.0.dist-info/WHEEL
epic_mace-0.5.0.dist-info/entry_points.txt
epic_mace-0.5.0.dist-info/top_level.txt
epic_mace-0.5.0.dist-info/RECORD
