Metadata-Version: 2.1
Name: epic-mace
Version: 0.5.0
Summary: Python library and command-line tool for generation of 3D coordinates for complexes of d-/f-elements
Home-page: http://github.com/EPiCs-group/mace
Author: Ivan Yu. Chernyshov
Author-email: ivan.chernyshoff@gmail.com
License: GPLv3+
Keywords: stereomers 3D embedding geometry complex
Classifier: Development Status :: 4 - Beta
Classifier: License :: OSI Approved :: GNU General Public License v3 or later (GPLv3+)
Classifier: Programming Language :: Python :: 3
Classifier: Topic :: Scientific/Engineering :: Chemistry
Requires-Python: >=3.7
License-File: LICENSE
Requires-Dist: numpy
Requires-Dist: pyyaml
